pyocle/__init__.py
pyocle/config.py
pyocle/form.py
pyocle/response.py
pyocle/serialization.py
pyocle/service/__init__.py
pyocle/service/core.py
pyocle/service/kms.py
pyocle/service/ses.py
pyocle/service/sns.py
tests/service/__init__.py
tests/service/test_core.py
tests/service/test_kms.py
tests/service/test_ses.py
tests/service/test_sns.py
pyocle-0.4.2.dist-info/LICENSE.txt
pyocle-0.4.2.dist-info/METADATA
pyocle-0.4.2.dist-info/WHEEL
pyocle-0.4.2.dist-info/top_level.txt
pyocle-0.4.2.dist-info/RECORD
