Metadata-Version: 2.1
Name: pyocle
Version: 0.4.2
Summary: Common library used alongside jsexton-portfolio chalice applications.
Home-page: https://github.com/jsexton-portfolio/pyocle.git
Author: Justin Sexton
Author-email: justinsexton.dev@gmail.com
License: MIT
Keywords: library,chalice
Platform: UNKNOWN
Classifier: Programming Language :: Python :: 3
Classifier: License :: OSI Approved :: MIT License
Classifier: Operating System :: OS Independent
Requires-Python: >=3
Requires-Dist: pydantic
Requires-Dist: boto3
Requires-Dist: jsonpickle
Requires-Dist: chalice
